{
	"municipalities": {
		"municipality": [
			{
				"knnr": "1440",
				"name": "Ale kommun",
				"url": "ale.se",
				"contact": "FEL",
				"dnsSecSigned": false,
				"isRecursive": false,
				"ipWww": false,
				"ipDns": false,
				"ipMail": false,
				"dnsList": [
				],
				"errors": [
				],
				"warnings": [
				]
			},
			{
				"knnr": "1489",
				"name": "Alings&aring;s kommun",
				"url": "alingsas.se",
				"contact": "FEL",
				"dnsSecSigned": false,
				"isRecursive": false,
				"ipWww": false,
				"ipDns": true,
				"ipMail": false,
				"dnsList": [
				],
				"errors": [
				],
				"warnings": [
					{"description": "Name server nic.alingsas.se (193.235.139.3) is recursive."}
				]
			},
			{
				"knnr": "0764",
				"name": "Alvesta kommun",
				"url": "alvesta.se",
				"contact": "FEL",
				"dnsSecSigned": false,
				"isRecursive": false,
				"ipWww": false,
				"ipDns": true,
				"ipMail": false,
				"dnsList": [
				],
				"errors": [
				],
				"warnings": [
				]
			},
			{
				"knnr": "0604",
				"name": "Aneby kommun",
				"url": "aneby.se",
				"contact": "FEL",
				"dnsSecSigned": false,
				"isRecursive": false,
				"ipWww": false,
				"ipDns": false,
				"ipMail": false,
				"dnsList": [
				],
				"errors": [
				],
				"warnings": [
				]
			},
			{
				"knnr": "1984",
				"name": "Arboga kommun",
				"url": "arboga.se",
				"contact": "FEL",
				"dnsSecSigned": false,
				"isRecursive": false,
				"ipWww": false,
				"ipDns": false,
				"ipMail": false,
				"dnsList": [
				],
				"errors": [
				],
				"warnings": [
				]
			},
			{
				"knnr": "2506",
				"name": "Arjeplogs kommun",
				"url": "arjeplog.se",
				"contact": "FEL",
				"dnsSecSigned": false,
				"isRecursive": false,
				"ipWww": false,
				"ipDns": false,
				"ipMail": false,
				"dnsList": [
				],
				"errors": [
				],
				"warnings": [
					{"description": "Delivery over IPv4 to hostmaster@arjeplog.se could not be done."},
					{"description": "Failed to deliver email for SOA RNAME of arjeplog.se (hostmaster.arjeplog.se) using hostmaster@arjeplog.se."}
				]
			},
			{
				"knnr": "2505",
				"name": "Arvidsjaurs kommun",
				"url": "arvidsjaur.se",
				"contact": "FEL",
				"dnsSecSigned": false,
				"isRecursive": false,
				"ipWww": false,
				"ipDns": true,
				"ipMail": false,
				"dnsList": [
				],
				"errors": [
				],
				"warnings": [
				]
			},
			{
				"knnr": "1784",
				"name": "Arvika kommun",
				"url": "arvika.se",
				"contact": "FEL",
				"dnsSecSigned": false,
				"isRecursive": false,
				"ipWww": false,
				"ipDns": false,
				"ipMail": false,
				"dnsList": [
				],
				"errors": [
				],
				"warnings": [
				]
			},
			{
				"knnr": "1882",
				"name": "Askersunds kommun",
				"url": "askersund.se",
				"contact": "FEL",
				"dnsSecSigned": false,
				"isRecursive": false,
				"ipWww": false,
				"ipDns": false,
				"ipMail": false,
				"dnsList": [
				],
				"errors": [
					{"description": "No address found for dns2.hallsberg.se."},
					{"description": "Host name or address error for dns2.hallsberg.se."}
				],
				"warnings": [
				]
			},
			{
				"knnr": "2084",
				"name": "Avesta kommun",
				"url": "avesta.se",
				"contact": "FEL",
				"dnsSecSigned": false,
				"isRecursive": false,
				"ipWww": false,
				"ipDns": false,
				"ipMail": false,
				"dnsList": [
				],
				"errors": [
				],
				"warnings": [
				]
			},
			{
				"knnr": "1460",
				"name": "Bengtsfors kommun",
				"url": "bengtsfors.se",
				"contact": "FEL",
				"dnsSecSigned": false,
				"isRecursive": false,
				"ipWww": false,
				"ipDns": false,
				"ipMail": false,
				"dnsList": [
				],
				"errors": [
				],
				"warnings": [
					{"description": "Name server ns2.dalsnet.se (194.17.150.10) is recursive."}
				]
			},
			{
				"knnr": "2326",
				"name": "Bergs kommun",
				"url": "berg.se",
				"contact": "FEL",
				"dnsSecSigned": false,
				"isRecursive": false,
				"ipWww": false,
				"ipDns": false,
				"ipMail": false,
				"dnsList": [
				],
				"errors": [
				],
				"warnings": [
				]
			},
			{
				"knnr": "2403",
				"name": "Bjurholms kommun",
				"url": "bjurholm.se",
				"contact": "FEL",
				"dnsSecSigned": false,
				"isRecursive": false,
				"ipWww": false,
				"ipDns": false,
				"ipMail": false,
				"dnsList": [
				],
				"errors": [
				],
				"warnings": [
					{"description": "Name server ns.bjurholm.se (80.88.100.139) is recursive."},
					{"description": "Delivery over IPv4 to hostmaster@ns.bjurholm.se could not be done."},
					{"description": "Failed to deliver email for SOA RNAME of bjurholm.se (hostmaster.ns.bjurholm.se) using hostmaster@ns.bjurholm.se."}
				]
			},
			{
				"knnr": "1260",
				"name": "Bjuvs kommun",
				"url": "bjuv.se",
				"contact": "FEL",
				"dnsSecSigned": false,
				"isRecursive": false,
				"ipWww": false,
				"ipDns": false,
				"ipMail": false,
				"dnsList": [
				],
				"errors": [
				],
				"warnings": [
				]
			},
			{
				"knnr": "2582",
				"name": "Bodens kommun",
				"url": "boden.se",
				"contact": "FEL",
				"dnsSecSigned": false,
				"isRecursive": false,
				"ipWww": false,
				"ipDns": false,
				"ipMail": false,
				"dnsList": [
				],
				"errors": [
				],
				"warnings": [
				]
			},
			{
				"knnr": "1443",
				"name": "Bollebygds kommun",
				"url": "bollebygd.se",
				"contact": "FEL",
				"dnsSecSigned": false,
				"isRecursive": false,
				"ipWww": false,
				"ipDns": false,
				"ipMail": true,
				"dnsList": [
				],
				"errors": [
				],
				"warnings": [
				]
			},
			{
				"knnr": "2183",
				"name": "Bolln&auml;s kommun",
				"url": "bollnas.se",
				"contact": "FEL",
				"dnsSecSigned": false,
				"isRecursive": false,
				"ipWww": false,
				"ipDns": true,
				"ipMail": false,
				"dnsList": [
				],
				"errors": [
				],
				"warnings": [
				]
			},
			{
				"knnr": "0885",
				"name": "Borgholms kommun",
				"url": "borgholm.se",
				"contact": "FEL",
				"dnsSecSigned": false,
				"isRecursive": false,
				"ipWww": false,
				"ipDns": false,
				"ipMail": false,
				"dnsList": [
				],
				"errors": [
				],
				"warnings": [
					{"description": "Name server bhmg.borgholm.se (194.218.96.253) is recursive."},
					{"description": "SOA expire to low 86400 seconds,1 days 0 hours,"}
				]
			},
			{
				"knnr": "2081",
				"name": "Borl&auml;nge kommun",
				"url": "borlange.se",
				"contact": "FEL",
				"dnsSecSigned": false,
				"isRecursive": false,
				"ipWww": false,
				"ipDns": false,
				"ipMail": false,
				"dnsList": [
				],
				"errors": [
					{"description": "DNS SERVFAIL when querying 91.195.225.2 for SOA"},
					{"description": "Name server ns2.borlange.se (91.195.225.2) does not answer queries over TCP."}
				],
				"warnings": [
				]
			},
			{
				"knnr": "1490",
				"name": "Bor&aring;s stad",
				"url": "boras.se",
				"contact": "FEL",
				"dnsSecSigned": false,
				"isRecursive": false,
				"ipWww": false,
				"ipDns": false,
				"ipMail": false,
				"dnsList": [
				],
				"errors": [
				],
				"warnings": [
					{"description": "SOA expire to low 86400 seconds,1 days 0 hours,"}
				]
			},
			{
				"knnr": "0127",
				"name": "Botkyrka kommun",
				"url": "botkyrka.se",
				"contact": "FEL",
				"dnsSecSigned": false,
				"isRecursive": false,
				"ipWww": false,
				"ipDns": false,
				"ipMail": false,
				"dnsList": [
				],
				"errors": [
				],
				"warnings": [
					{"description": "SOA expire to low 86400 seconds,1 days 0 hours,"}
				]
			},
			{
				"knnr": "0560",
				"name": "Boxholms kommun",
				"url": "boxholm.se",
				"contact": "FEL",
				"dnsSecSigned": false,
				"isRecursive": false,
				"ipWww": false,
				"ipDns": false,
				"ipMail": false,
				"dnsList": [
				],
				"errors": [
				],
				"warnings": [
				]
			},
			{
				"knnr": "1272",
				"name": "Brom&ouml;lla kommun",
				"url": "bromolla.se",
				"contact": "FEL",
				"dnsSecSigned": false,
				"isRecursive": false,
				"ipWww": false,
				"ipDns": false,
				"ipMail": false,
				"dnsList": [
				],
				"errors": [
				],
				"warnings": [
				]
			},
			{
				"knnr": "2305",
				"name": "Br&auml;cke kommun",
				"url": "bracke.se",
				"contact": "FEL",
				"dnsSecSigned": false,
				"isRecursive": false,
				"ipWww": false,
				"ipDns": false,
				"ipMail": false,
				"dnsList": [
				],
				"errors": [
				],
				"warnings": [
				]
			},
			{
				"knnr": "1231",
				"name": "Burl&ouml;vs kommun",
				"url": "burlov.se",
				"contact": "FEL",
				"dnsSecSigned": false,
				"isRecursive": false,
				"ipWww": false,
				"ipDns": false,
				"ipMail": false,
				"dnsList": [
				],
				"errors": [
				],
				"warnings": [
					{"description": "SOA expire to low 86400 seconds,1 days 0 hours,"}
				]
			},
			{
				"knnr": "1278",
				"name": "B&aring;stads kommun",
				"url": "bastad.se",
				"contact": "FEL",
				"dnsSecSigned": false,
				"isRecursive": false,
				"ipWww": false,
				"ipDns": false,
				"ipMail": false,
				"dnsList": [
				],
				"errors": [
					{"description": "Name server ns3.bjare.net (85.30.62.58) not authoritative for bastad.se."}
				],
				"warnings": [
					{"description": "Name server ns2.bjare.net (217.9.208.194) is recursive."},
					{"description": "Delivery over IPv4 to hostmaster@ns.bastad.se could not be done."},
					{"description": "Failed to deliver email for SOA RNAME of bastad.se (hostmaster.ns.bastad.se) using hostmaster@ns.bastad.se."}
				]
			},
			{
				"knnr": "1438",
				"name": "Dals-Eds kommun",
				"url": "dalsed.se",
				"contact": "FEL",
				"dnsSecSigned": false,
				"isRecursive": false,
				"ipWww": false,
				"ipDns": false,
				"ipMail": false,
				"dnsList": [
				],
				"errors": [
				],
				"warnings": [
					{"description": "Name server ns2.dalsnet.se (194.17.150.10) is recursive."}
				]
			},
			{
				"knnr": "0162",
				"name": "Danderyds kommun",
				"url": "danderyd.se",
				"contact": "FEL",
				"dnsSecSigned": false,
				"isRecursive": false,
				"ipWww": false,
				"ipDns": true,
				"ipMail": false,
				"dnsList": [
				],
				"errors": [
				],
				"warnings": [
				]
			},
			{
				"knnr": "1862",
				"name": "Degerfors kommun",
				"url": "degerfors.se",
				"contact": "FEL",
				"dnsSecSigned": false,
				"isRecursive": false,
				"ipWww": false,
				"ipDns": true,
				"ipMail": false,
				"dnsList": [
				],
				"errors": [
				],
				"warnings": [
				]
			},
			{
				"knnr": "2425",
				"name": "Dorotea kommun",
				"url": "dorotea.se",
				"contact": "FEL",
				"dnsSecSigned": false,
				"isRecursive": false,
				"ipWww": false,
				"ipDns": false,
				"ipMail": false,
				"dnsList": [
				],
				"errors": [
				],
				"warnings": [
				]
			},
			{
				"knnr": "1730",
				"name": "Eda kommun",
				"url": "eda.se",
				"contact": "FEL",
				"dnsSecSigned": false,
				"isRecursive": false,
				"ipWww": false,
				"ipDns": true,
				"ipMail": false,
				"dnsList": [
				],
				"errors": [
				],
				"warnings": [
				]
			},
			{
				"knnr": "0125",
				"name": "Eker&ouml; kommun",
				"url": "ekero.se",
				"contact": "FEL",
				"dnsSecSigned": false,
				"isRecursive": false,
				"ipWww": false,
				"ipDns": false,
				"ipMail": false,
				"dnsList": [
				],
				"errors": [
				],
				"warnings": [
				]
			},
			{
				"knnr": "0686",
				"name": "Eksj&ouml; kommun",
				"url": "eksjo.se",
				"contact": "FEL",
				"dnsSecSigned": false,
				"isRecursive": false,
				"ipWww": false,
				"ipDns": false,
				"ipMail": false,
				"dnsList": [
				],
				"errors": [
				],
				"warnings": [
					{"description": "Name server dns01.hoglandet.se (178.22.200.34) is recursive."},
					{"description": "Name server dns02.hoglandet.se (178.22.200.66) is recursive."}
				]
			},
			{
				"knnr": "0862",
				"name": "Emmaboda kommun",
				"url": "emmaboda.se",
				"contact": "FEL",
				"dnsSecSigned": false,
				"isRecursive": false,
				"ipWww": false,
				"ipDns": false,
				"ipMail": false,
				"dnsList": [
				],
				"errors": [
				],
				"warnings": [
				]
			},
			{
				"knnr": "0381",
				"name": "Enk&ouml;pings kommun",
				"url": "enkoping.se",
				"contact": "FEL",
				"dnsSecSigned": false,
				"isRecursive": false,
				"ipWww": false,
				"ipDns": false,
				"ipMail": false,
				"dnsList": [
				],
				"errors": [
				],
				"warnings": [
				]
			},
			{
				"knnr": "0484",
				"name": "Eskilstuna kommun",
				"url": "eskilstuna.se",
				"contact": "FEL",
				"dnsSecSigned": false,
				"isRecursive": false,
				"ipWww": false,
				"ipDns": false,
				"ipMail": false,
				"dnsList": [
				],
				"errors": [
				],
				"warnings": [
					{"description": "Delivery over IPv4 to root@eskilstuna.se could not be done."},
					{"description": "Failed to deliver email for SOA RNAME of eskilstuna.se (root.eskilstuna.se) using root@eskilstuna.se."}
				]
			},
			{
				"knnr": "1285",
				"name": "Esl&ouml;vs kommun",
				"url": "eslov.se",
				"contact": "FEL",
				"dnsSecSigned": false,
				"isRecursive": false,
				"ipWww": false,
				"ipDns": false,
				"ipMail": false,
				"dnsList": [
				],
				"errors": [
					{"description": "Name server kista.dns.swip.net (192.71.220.9) not authoritative for eslov.se."},
					{"description": "Name server malmoe.dns.swip.net (192.71.180.44) not authoritative for eslov.se."}
				],
				"warnings": [
					{"description": "Name server umbrella.eslov.se (194.68.85.11) is recursive."}
				]
			},
			{
				"knnr": "1445",
				"name": "Essunga kommun",
				"url": "essunga.se",
				"contact": "FEL",
				"dnsSecSigned": false,
				"isRecursive": false,
				"ipWww": false,
				"ipDns": false,
				"ipMail": false,
				"dnsList": [
				],
				"errors": [
				],
				"warnings": [
					{"description": "SOA expire to low 28800 seconds,0 days 8 hours,"}
				]
			},
			{
				"knnr": "1982",
				"name": "Fagersta kommun",
				"url": "fagersta.se",
				"contact": "FEL",
				"dnsSecSigned": false,
				"isRecursive": false,
				"ipWww": false,
				"ipDns": false,
				"ipMail": false,
				"dnsList": [
				],
				"errors": [
				],
				"warnings": [
					{"description": "SOA expire to low 86400 seconds,1 days 0 hours,"}
				]
			},
			{
				"knnr": "1382",
				"name": "Falkenbergs kommun",
				"url": "falkenberg.se",
				"contact": "FEL",
				"dnsSecSigned": false,
				"isRecursive": false,
				"ipWww": false,
				"ipDns": false,
				"ipMail": false,
				"dnsList": [
				],
				"errors": [
				],
				"warnings": [
				]
			},
			{
				"knnr": "1499",
				"name": "Falk&ouml;pings kommun",
				"url": "falkoping.se",
				"contact": "FEL",
				"dnsSecSigned": false,
				"isRecursive": false,
				"ipWww": false,
				"ipDns": false,
				"ipMail": false,
				"dnsList": [
				],
				"errors": [
				],
				"warnings": [
				]
			},
			{
				"knnr": "2080",
				"name": "Falun kommun",
				"url": "falun.se",
				"contact": "FEL",
				"dnsSecSigned": false,
				"isRecursive": false,
				"ipWww": false,
				"ipDns": true,
				"ipMail": false,
				"dnsList": [
				],
				"errors": [
				],
				"warnings": [
					{"description": "Delivery over IPv4 to hostmaster@falun.se could not be done."},
					{"description": "Failed to deliver email for SOA RNAME of falun.se (hostmaster.falun.se) using hostmaster@falun.se."}
				]
			},
			{
				"knnr": "1782",
				"name": "Filipstads kommun",
				"url": "filipstad.se",
				"contact": "FEL",
				"dnsSecSigned": false,
				"isRecursive": false,
				"ipWww": false,
				"ipDns": false,
				"ipMail": false,
				"dnsList": [
				],
				"errors": [
					{"description": "Too few name servers (1)."},
					{"description": "Too few IPv4 name servers (1)."}
				],
				"warnings": [
				]
			},
			{
				"knnr": "0562",
				"name": "Finsp&aring;ngs kommun",
				"url": "finspong.se",
				"contact": "FEL",
				"dnsSecSigned": false,
				"isRecursive": false,
				"ipWww": false,
				"ipDns": false,
				"ipMail": false,
				"dnsList": [
				],
				"errors": [
				],
				"warnings": [
				]
			},
			{
				"knnr": "0482",
				"name": "Flens kommun",
				"url": "flen.se",
				"contact": "FEL",
				"dnsSecSigned": false,
				"isRecursive": false,
				"ipWww": false,
				"ipDns": false,
				"ipMail": false,
				"dnsList": [
				],
				"errors": [
				],
				"warnings": [
				]
			},
			{
				"knnr": "1763",
				"name": "Forshaga kommun",
				"url": "forshaga.se",
				"contact": "FEL",
				"dnsSecSigned": false,
				"isRecursive": false,
				"ipWww": false,
				"ipDns": false,
				"ipMail": false,
				"dnsList": [
				],
				"errors": [
				],
				"warnings": [
					{"description": "Name server fk-dns01.forshaga.se (212.28.197.33) is recursive."},
					{"description": "Name server fk-dns02.forshaga.se (212.28.197.34) is recursive."}
				]
			},
			{
				"knnr": "1439",
				"name": "F&auml;rgelanda kommun",
				"url": "fargelanda.se",
				"contact": "FEL",
				"dnsSecSigned": false,
				"isRecursive": false,
				"ipWww": false,
				"ipDns": false,
				"ipMail": false,
				"dnsList": [
				],
				"errors": [
				],
				"warnings": [
				]
			},
			{
				"knnr": "2026",
				"name": "Gagnefs kommun",
				"url": "gagnef.se",
				"contact": "FEL",
				"dnsSecSigned": false,
				"isRecursive": false,
				"ipWww": false,
				"ipDns": false,
				"ipMail": false,
				"dnsList": [
				],
				"errors": [
				],
				"warnings": [
				]
			},
			{
				"knnr": "0662",
				"name": "Gislaveds kommun",
				"url": "gislaved.se",
				"contact": "FEL",
				"dnsSecSigned": false,
				"isRecursive": false,
				"ipWww": false,
				"ipDns": false,
				"ipMail": false,
				"dnsList": [
				],
				"errors": [
				],
				"warnings": [
				]
			},
			{
				"knnr": "0461",
				"name": "Gnesta kommun",
				"url": "gnesta.se",
				"contact": "FEL",
				"dnsSecSigned": false,
				"isRecursive": false,
				"ipWww": false,
				"ipDns": false,
				"ipMail": false,
				"dnsList": [
				],
				"errors": [
				],
				"warnings": [
				]
			},
			{
				"knnr": "0617",
				"name": "Gnosj&ouml; kommun",
				"url": "gnosjo.se",
				"contact": "FEL",
				"dnsSecSigned": false,
				"isRecursive": false,
				"ipWww": false,
				"ipDns": false,
				"ipMail": false,
				"dnsList": [
				],
				"errors": [
				],
				"warnings": [
				]
			},
			{
				"knnr": "0980",
				"name": "Gotlands kommun",
				"url": "gotland.se",
				"contact": "FEL",
				"dnsSecSigned": false,
				"isRecursive": false,
				"ipWww": false,
				"ipDns": false,
				"ipMail": false,
				"dnsList": [
				],
				"errors": [
					{"description": "Not enough valid signatures over SOA RRset found for gotland.se."}
				],
				"warnings": [
					{"description": "Name server ns.gotland.se (193.180.228.194) is recursive."},
					{"description": "Broken chain of trust for gotland.se - DNSKEY found at child, but no DS was found at parent."},
					{"description": "DNSSEC signature expired: RRSIG(gotland.se/IN/DNSKEY/45218)"},
					{"description": "DNSSEC signature expired: RRSIG(gotland.se/IN/SOA/45218)"}
				]
			},
			{
				"knnr": "1764",
				"name": "Grums kommun",
				"url": "grums.se",
				"contact": "FEL",
				"dnsSecSigned": false,
				"isRecursive": false,
				"ipWww": false,
				"ipDns": false,
				"ipMail": false,
				"dnsList": [
				],
				"errors": [
				],
				"warnings": [
				]
			},
			{
				"knnr": "1444",
				"name": "Gr&auml;storps kommun",
				"url": "grastorp.se",
				"contact": "FEL",
				"dnsSecSigned": false,
				"isRecursive": false,
				"ipWww": false,
				"ipDns": false,
				"ipMail": false,
				"dnsList": [
				],
				"errors": [
				],
				"warnings": [
				]
			},
			{
				"knnr": "1447",
				"name": "Gullsp&aring;ngs kommun",
				"url": "gullspang.se",
				"contact": "FEL",
				"dnsSecSigned": false,
				"isRecursive": false,
				"ipWww": false,
				"ipDns": false,
				"ipMail": false,
				"dnsList": [
				],
				"errors": [
					{"description": "Name server ns1.mteab.net (80.254.240.18) does not answer queries over TCP."}
				],
				"warnings": [
					{"description": "Name server ns1.mteab.net (80.254.240.18) is recursive."}
				]
			},
			{
				"knnr": "2523",
				"name": "G&auml;llivare kommun",
				"url": "gellivare.se",
				"contact": "FEL",
				"dnsSecSigned": false,
				"isRecursive": false,
				"ipWww": false,
				"ipDns": false,
				"ipMail": false,
				"dnsList": [
				],
				"errors": [
					{"description": "Too few name servers (1)."},
					{"description": "Too few IPv4 name servers (1)."}
				],
				"warnings": [
				]
			},
			{
				"knnr": "2180",
				"name": "G&auml;vle kommun",
				"url": "gavle.se",
				"contact": "FEL",
				"dnsSecSigned": false,
				"isRecursive": false,
				"ipWww": false,
				"ipDns": true,
				"ipMail": false,
				"dnsList": [
				],
				"errors": [
				],
				"warnings": [
					{"description": "Name server ns2.gavlenet.com (213.141.64.3) is recursive."},
					{"description": "Name server ns2.gavlenet.com (2001:b48:0:0:0:0:0:3) is recursive."}
				]
			},
			{
				"knnr": "1480",
				"name": "G&ouml;teborgs Stad",
				"url": "goteborg.se",
				"contact": "FEL",
				"dnsSecSigned": false,
				"isRecursive": false,
				"ipWww": false,
				"ipDns": false,
				"ipMail": false,
				"dnsList": [
				],
				"errors": [
				],
				"warnings": [
				]
			},
			{
				"knnr": "1471",
				"name": "G&ouml;tene kommun",
				"url": "gotene.se",
				"contact": "FEL",
				"dnsSecSigned": false,
				"isRecursive": false,
				"ipWww": false,
				"ipDns": false,
				"ipMail": false,
				"dnsList": [
				],
				"errors": [
				],
				"warnings": [
				]
			},
			{
				"knnr": "0643",
				"name": "Habo kommun",
				"url": "habokommun.se",
				"contact": "FEL",
				"dnsSecSigned": false,
				"isRecursive": false,
				"ipWww": false,
				"ipDns": false,
				"ipMail": false,
				"dnsList": [
				],
				"errors": [
				],
				"warnings": [
					{"description": "Name server ns.habo.net (80.244.198.5) is recursive."}
				]
			},
			{
				"knnr": "1783",
				"name": "Hagfors kommun",
				"url": "hagfors.se",
				"contact": "FEL",
				"dnsSecSigned": false,
				"isRecursive": false,
				"ipWww": true,
				"ipDns": true,
				"ipMail": true,
				"dnsList": [
				],
				"errors": [
				],
				"warnings": [
					{"description": "Could not find reverse address for 2001:2040:23:0:0:0:0:10 (0.1.0.0.0.0.0.0.0.0.0.0.0.0.0.0.0.0.0.0.3.2.0.0.0.4.0.2.1.0.0.2.ip6.arpa.)."},
					{"description": "Could not find reverse address for 2001:2040:23:0:0:0:0:10 (0.1.0.0.0.0.0.0.0.0.0.0.0.0.0.0.0.0.0.0.3.2.0.0.0.4.0.2.1.0.0.2.ip6.arpa.)."},
					{"description": "Could not find reverse address for 2001:2040:23:0:0:0:0:50 (0.5.0.0.0.0.0.0.0.0.0.0.0.0.0.0.0.0.0.0.3.2.0.0.0.4.0.2.1.0.0.2.ip6.arpa.)."}
				]
			},
			{
				"knnr": "1861",
				"name": "Hallsbergs kommun",
				"url": "hallsberg.se",
				"contact": "FEL",
				"dnsSecSigned": false,
				"isRecursive": false,
				"ipWww": false,
				"ipDns": false,
				"ipMail": false,
				"dnsList": [
				],
				"errors": [
					{"description": "No address found for dns2.hallsberg.se."},
					{"description": "Host name or address error for dns2.hallsberg.se."},
					{"description": "Name server kista.dns.swip.net (192.71.220.9) not authoritative for hallsberg.se."}
				],
				"warnings": [
				]
			},
			{
				"knnr": "1961",
				"name": "Hallstahammars kommun",
				"url": "hallstahammar.se",
				"contact": "FEL",
				"dnsSecSigned": false,
				"isRecursive": false,
				"ipWww": false,
				"ipDns": false,
				"ipMail": false,
				"dnsList": [
				],
				"errors": [
				],
				"warnings": [
					{"description": "Name server ns01.centralpark.se (217.78.26.157) is recursive."},
					{"description": "SOA expire to low 86400 seconds,1 days 0 hours,"}
				]
			},
			{
				"knnr": "1380",
				"name": "Halmstads kommun",
				"url": "halmstad.se",
				"contact": "FEL",
				"dnsSecSigned": false,
				"isRecursive": false,
				"ipWww": false,
				"ipDns": false,
				"ipMail": false,
				"dnsList": [
				],
				"errors": [
				],
				"warnings": [
				]
			},
			{
				"knnr": "1761",
				"name": "Hammar&ouml; kommun",
				"url": "hammaro.se",
				"contact": "FEL",
				"dnsSecSigned": false,
				"isRecursive": false,
				"ipWww": false,
				"ipDns": false,
				"ipMail": false,
				"dnsList": [
				],
				"errors": [
				],
				"warnings": [
				]
			},
			{
				"knnr": "0136",
				"name": "Haninge kommun",
				"url": "haninge.se",
				"contact": "FEL",
				"dnsSecSigned": false,
				"isRecursive": false,
				"ipWww": false,
				"ipDns": false,
				"ipMail": false,
				"dnsList": [
				],
				"errors": [
				],
				"warnings": [
				]
			},
			{
				"knnr": "2583",
				"name": "Haparanda stad",
				"url": "haparanda.se",
				"contact": "FEL",
				"dnsSecSigned": false,
				"isRecursive": false,
				"ipWww": false,
				"ipDns": false,
				"ipMail": false,
				"dnsList": [
				],
				"errors": [
				],
				"warnings": [
				]
			},
			{
				"knnr": "0331",
				"name": "Heby kommun",
				"url": "heby.se",
				"contact": "FEL",
				"dnsSecSigned": false,
				"isRecursive": false,
				"ipWww": false,
				"ipDns": false,
				"ipMail": false,
				"dnsList": [
				],
				"errors": [
				],
				"warnings": [
				]
			},
			{
				"knnr": "2083",
				"name": "Hedemora kommun",
				"url": "hedemora.se",
				"contact": "FEL",
				"dnsSecSigned": false,
				"isRecursive": false,
				"ipWww": false,
				"ipDns": false,
				"ipMail": false,
				"dnsList": [
				],
				"errors": [
					{"description": "EDNS not supported by 195.67.100.210."}
				],
				"warnings": [
					{"description": "Reverse for 212.112.38.42 points to an unknown host name (212-112-38-42.hedemora.se)."},
					{"description": "Reverse for 212.112.38.42 points to an unknown host name (212-112-38-42.hedemora.se)."},
					{"description": "SOA expire to low 86400 seconds,1 days 0 hours,"}
				]
			},
			{
				"knnr": "1283",
				"name": "Helsingborgs stad",
				"url": "helsingborg.se",
				"contact": "FEL",
				"dnsSecSigned": false,
				"isRecursive": false,
				"ipWww": false,
				"ipDns": false,
				"ipMail": false,
				"dnsList": [
				],
				"errors": [
				],
				"warnings": [
				]
			},
			{
				"knnr": "1466",
				"name": "Herrljunga kommun",
				"url": "herrljunga.se",
				"contact": "FEL",
				"dnsSecSigned": false,
				"isRecursive": false,
				"ipWww": false,
				"ipDns": false,
				"ipMail": false,
				"dnsList": [
				],
				"errors": [
					{"description": "Superfluous name server listed at parent: ns.tranemo.se"}
				],
				"warnings": [
					{"description": "Name server dns1.jra.se (81.25.144.94) is recursive."},
					{"description": "Name server dns2.jra.se (81.25.152.2) is recursive."},
					{"description": "Delivery over IPv4 to hostmaster@jra.se could not be done."},
					{"description": "Failed to deliver email for SOA RNAME of herrljunga.se (hostmaster.jra.se) using hostmaster@jra.se."}
				]
			},
			{
				"knnr": "1497",
				"name": "Hjo kommun",
				"url": "hjo.se",
				"contact": "FEL",
				"dnsSecSigned": false,
				"isRecursive": false,
				"ipWww": false,
				"ipDns": false,
				"ipMail": true,
				"dnsList": [
				],
				"errors": [
				],
				"warnings": [
				]
			},
			{
				"knnr": "2104",
				"name": "Hofors kommun",
				"url": "hofors.se",
				"contact": "FEL",
				"dnsSecSigned": false,
				"isRecursive": false,
				"ipWww": false,
				"ipDns": false,
				"ipMail": true,
				"dnsList": [
				],
				"errors": [
					{"description": "EDNS not supported by 87.255.160.20."},
					{"description": "EDNS not supported by 87.255.160.10."}
				],
				"warnings": [
				]
			},
			{
				"knnr": "0126",
				"name": "Huddinge kommun",
				"url": "huddinge.se",
				"contact": "FEL",
				"dnsSecSigned": false,
				"isRecursive": false,
				"ipWww": false,
				"ipDns": false,
				"ipMail": false,
				"dnsList": [
				],
				"errors": [
				],
				"warnings": [
				]
			},
			{
				"knnr": "2184",
				"name": "Hudiksvalls kommun",
				"url": "hudiksvall.se",
				"contact": "FEL",
				"dnsSecSigned": false,
				"isRecursive": false,
				"ipWww": false,
				"ipDns": true,
				"ipMail": false,
				"dnsList": [
				],
				"errors": [
				],
				"warnings": [
				]
			},
			{
				"knnr": "0860",
				"name": "Hultsfreds kommun",
				"url": "hultsfred.se",
				"contact": "FEL",
				"dnsSecSigned": false,
				"isRecursive": false,
				"ipWww": false,
				"ipDns": false,
				"ipMail": false,
				"dnsList": [
				],
				"errors": [
				],
				"warnings": [
				]
			},
			{
				"knnr": "1315",
				"name": "Hylte kommun",
				"url": "hylte.se",
				"contact": "FEL",
				"dnsSecSigned": false,
				"isRecursive": false,
				"ipWww": false,
				"ipDns": false,
				"ipMail": false,
				"dnsList": [
				],
				"errors": [
					{"description": "Inconsistent glue for name server dns.hylte.se."},
					{"description": "Host name 213.50.52.130 is illegal (syntax error at Top all-numeric)"}
				],
				"warnings": [
					{"description": "Error while checking SOA MNAME for hylte.se (213.50.52.130)."}
				]
			},
			{
				"knnr": "0305",
				"name": "H&aring;bo kommun",
				"url": "habo.se",
				"contact": "FEL",
				"dnsSecSigned": false,
				"isRecursive": false,
				"ipWww": false,
				"ipDns": false,
				"ipMail": false,
				"dnsList": [
				],
				"errors": [
				],
				"warnings": [
				]
			},
			{
				"knnr": "1863",
				"name": "H&auml;llefors kommun",
				"url": "hellefors.se",
				"contact": "FEL",
				"dnsSecSigned": false,
				"isRecursive": false,
				"ipWww": false,
				"ipDns": false,
				"ipMail": false,
				"dnsList": [
				],
				"errors": [
				],
				"warnings": [
					{"description": "SOA expire to low 86400 seconds,1 days 0 hours,"}
				]
			},
			{
				"knnr": "2361",
				"name": "H&auml;rjedalens kommun",
				"url": "herjedalen.se",
				"contact": "FEL",
				"dnsSecSigned": false,
				"isRecursive": false,
				"ipWww": false,
				"ipDns": false,
				"ipMail": false,
				"dnsList": [
				],
				"errors": [
				],
				"warnings": [
				]
			},
			{
				"knnr": "2280",
				"name": "H&auml;rn&ouml;sands kommun",
				"url": "harnosand.se",
				"contact": "FEL",
				"dnsSecSigned": false,
				"isRecursive": false,
				"ipWww": false,
				"ipDns": false,
				"ipMail": false,
				"dnsList": [
				],
				"errors": [
				],
				"warnings": [
				]
			},
			{
				"knnr": "1401",
				"name": "H&auml;rryda kommun",
				"url": "harryda.se",
				"contact": "FEL",
				"dnsSecSigned": false,
				"isRecursive": false,
				"ipWww": false,
				"ipDns": false,
				"ipMail": false,
				"dnsList": [
				],
				"errors": [
				],
				"warnings": [
				]
			},
			{
				"knnr": "1293",
				"name": "H&auml;ssleholms kommun",
				"url": "hassleholm.se",
				"contact": "FEL",
				"dnsSecSigned": false,
				"isRecursive": false,
				"ipWww": false,
				"ipDns": false,
				"ipMail": false,
				"dnsList": [
				],
				"errors": [
					{"description": "Superfluous name server listed at parent: kista.dns.swip.net"},
					{"description": "Superfluous name server listed at parent: malmoe.dns.swip.net"},
					{"description": "Too few name servers (1)."}
				],
				"warnings": [
					{"description": "Reverse for 194.71.179.2 points to an unknown host name (google.politiker.hassleholm.se)."},
					{"description": "Name server ns.hassleholm.se (194.71.179.2) is recursive."},
					{"description": "Could not find reverse address for 192.121.255.34 (34.255.121.192.in-addr.arpa.)."},
					{"description": "Reverse for 194.71.179.2 points to an unknown host name (google.politiker.hassleholm.se)."},
					{"description": "Reverse for 194.71.179.2 points to an unknown host name (google.politiker.hassleholm.se)."},
					{"description": "Delivery over IPv4 to hostmaster@ns.hassleholm.se could not be done."},
					{"description": "Failed to deliver email for SOA RNAME of hassleholm.se (hostmaster.ns.hassleholm.se) using hostmaster@ns.hassleholm.se."}
				]
			},
			{
				"knnr": "1284",
				"name": "H&ouml;gan&auml;s kommun",
				"url": "hoganas.se",
				"contact": "FEL",
				"dnsSecSigned": false,
				"isRecursive": false,
				"ipWww": false,
				"ipDns": false,
				"ipMail": false,
				"dnsList": [
				],
				"errors": [
				],
				"warnings": [
				]
			},
			{
				"knnr": "0821",
				"name": "H&ouml;gsby kommun",
				"url": "hogsby.se",
				"contact": "FEL",
				"dnsSecSigned": false,
				"isRecursive": false,
				"ipWww": false,
				"ipDns": false,
				"ipMail": false,
				"dnsList": [
				],
				"errors": [
				],
				"warnings": [
					{"description": "SOA expire to low 86400 seconds,1 days 0 hours,"}
				]
			},
			{
				"knnr": "1266",
				"name": "H&ouml;rby kommun",
				"url": "horby.se",
				"contact": "FEL",
				"dnsSecSigned": false,
				"isRecursive": false,
				"ipWww": false,
				"ipDns": false,
				"ipMail": false,
				"dnsList": [
				],
				"errors": [
				],
				"warnings": [
				]
			},
			{
				"knnr": "1267",
				"name": "H&ouml;&ouml;rs kommun",
				"url": "hoor.se",
				"contact": "FEL",
				"dnsSecSigned": false,
				"isRecursive": false,
				"ipWww": false,
				"ipDns": false,
				"ipMail": false,
				"dnsList": [
				],
				"errors": [
				],
				"warnings": [
				]
			},
			{
				"knnr": "2510",
				"name": "Jokkmokks kommun",
				"url": "jokkmokk.se",
				"contact": "FEL",
				"dnsSecSigned": false,
				"isRecursive": false,
				"ipWww": false,
				"ipDns": true,
				"ipMail": false,
				"dnsList": [
				],
				"errors": [
				],
				"warnings": [
				]
			},
			{
				"knnr": "0123",
				"name": "J&auml;rf&auml;lla kommun",
				"url": "jarfalla.se",
				"contact": "FEL",
				"dnsSecSigned": false,
				"isRecursive": false,
				"ipWww": false,
				"ipDns": false,
				"ipMail": false,
				"dnsList": [
				],
				"errors": [
					{"description": "Too few name servers (1)."},
					{"description": "Name server dns1.jarfalla.se (62.20.90.27) does not answer queries over TCP."}
				],
				"warnings": [
					{"description": "SOA expire to low 3600 seconds,0 days 1 hours,"}
				]
			},
			{
				"knnr": "0680",
				"name": "J&ouml;nk&ouml;pings kommun",
				"url": "jonkoping.se",
				"contact": "FEL",
				"dnsSecSigned": false,
				"isRecursive": false,
				"ipWww": false,
				"ipDns": false,
				"ipMail": false,
				"dnsList": [
				],
				"errors": [
				],
				"warnings": [
				]
			},
			{
				"knnr": "2514",
				"name": "Kalix kommun",
				"url": "kalix.se",
				"contact": "FEL",
				"dnsSecSigned": false,
				"isRecursive": false,
				"ipWww": false,
				"ipDns": false,
				"ipMail": false,
				"dnsList": [
				],
				"errors": [
					{"description": "DNS SERVFAIL when querying 83.150.137.2 for SOA"},
					{"description": "Name server ns.linnea.net (83.150.137.2) does not answer queries over TCP."},
					{"description": "DNS SERVFAIL when querying 83.150.137.3 for SOA"},
					{"description": "Name server ns2.linnea.net (83.150.137.3) does not answer queries over TCP."}
				],
				"warnings": [
					{"description": "Could not find reverse address for 194.117.166.249 (249.166.117.194.in-addr.arpa.)."},
					{"description": "Name server dns0.kalix.se (194.117.166.249) is recursive."},
					{"description": "Could not find reverse address for 194.117.166.239 (239.166.117.194.in-addr.arpa.)."},
					{"description": "Name server dns1.kalix.se (194.117.166.239) is recursive."},
					{"description": "Could not find reverse address for 194.117.166.239 (239.166.117.194.in-addr.arpa.)."}
				]
			},
			{
				"knnr": "0880",
				"name": "Kalmar kommun",
				"url": "kalmar.se",
				"contact": "FEL",
				"dnsSecSigned": false,
				"isRecursive": false,
				"ipWww": false,
				"ipDns": false,
				"ipMail": false,
				"dnsList": [
				],
				"errors": [
				],
				"warnings": [
				]
			},
			{
				"knnr": "1446",
				"name": "Karlsborgs kommun",
				"url": "karlsborg.se",
				"contact": "FEL",
				"dnsSecSigned": false,
				"isRecursive": false,
				"ipWww": false,
				"ipDns": false,
				"ipMail": false,
				"dnsList": [
				],
				"errors": [
				],
				"warnings": [
					{"description": "Name server ns.karlsborg.se (80.68.117.2) is recursive."},
					{"description": "Delivery over IPv4 to hostmaster@ns.karlsborg.se could not be done."},
					{"description": "Failed to deliver email for SOA RNAME of karlsborg.se (hostmaster.ns.karlsborg.se) using hostmaster@ns.karlsborg.se."}
				]
			},
			{
				"knnr": "1082",
				"name": "Karlshamns kommun",
				"url": "karlshamn.se",
				"contact": "FEL",
				"dnsSecSigned": false,
				"isRecursive": false,
				"ipWww": false,
				"ipDns": true,
				"ipMail": false,
				"dnsList": [
				],
				"errors": [
				],
				"warnings": [
				]
			},
			{
				"knnr": "1883",
				"name": "Karlskoga kommun",
				"url": "karlskoga.se",
				"contact": "FEL",
				"dnsSecSigned": false,
				"isRecursive": false,
				"ipWww": false,
				"ipDns": false,
				"ipMail": false,
				"dnsList": [
				],
				"errors": [
					{"description": "Too few IPv4 name servers (1)."},
					{"description": "Missing glue at child: ns.sub.karlskoga.se"},
					{"description": "No address found for ns.sub.karlskoga.se."},
					{"description": "Host name or address error for ns.sub.karlskoga.se."}
				],
				"warnings": [
					{"description": "Delivery over IPv4 to hostmaster@ns.karlskoga.se could not be done."},
					{"description": "Failed to deliver email for SOA RNAME of karlskoga.se (hostmaster.ns.karlskoga.se) using hostmaster@ns.karlskoga.se."}
				]
			},
			{
				"knnr": "1080",
				"name": "Karlskrona kommun",
				"url": "karlskrona.se",
				"contact": "FEL",
				"dnsSecSigned": false,
				"isRecursive": false,
				"ipWww": false,
				"ipDns": false,
				"ipMail": false,
				"dnsList": [
				],
				"errors": [
					{"description": "Name server ns2.karlskrona.se (194.68.105.101) does not answer queries over UDP."},
					{"description": "Name server ns2.karlskrona.se (194.68.105.101) does not answer queries over TCP."}
				],
				"warnings": [
				]
			},
			{
				"knnr": "1780",
				"name": "Karlstads kommun",
				"url": "karlstad.se",
				"contact": "FEL",
				"dnsSecSigned": false,
				"isRecursive": false,
				"ipWww": false,
				"ipDns": false,
				"ipMail": false,
				"dnsList": [
				],
				"errors": [
				],
				"warnings": [
					{"description": "Name server dns1.karlstad.se (193.235.28.225) is recursive."},
					{"description": "Delivery over IPv4 to hostmaster@karlstad.se could not be done."},
					{"description": "Failed to deliver email for SOA RNAME of karlstad.se (hostmaster.karlstad.se) using hostmaster@karlstad.se."}
				]
			},
			{
